Container/Container.py
Container/__init__.py
Container/dataclasses.py
Container/enums.py
Container/generales.py
util_container-1.0.0.dist-info/METADATA
util_container-1.0.0.dist-info/WHEEL
util_container-1.0.0.dist-info/licenses/LICENSE
util_container-1.0.0.dist-info/RECORD
