Metadata-Version: 2.4
Name: util-container
Version: 1.0.0
Summary: Utilidades para trabajar con clases inspiradas en programación funcional.
Author-email: Iván Sayavedra <sayaivan@gmail.com>
License-File: LICENSE
Classifier: License :: OSI Approved :: MIT License
Classifier: Operating System :: OS Independent
Classifier: Programming Language :: Python :: 3
Requires-Python: >=3.11
